{
  "aggregate": {
    "timestamp": "2020-07-14T16:32:43.801Z",
    "scenariosCreated": 17999,
    "scenariosCompleted": 2983,
    "requestsCompleted": 2983,
    "latency": {
      "min": 104.2,
      "max": 60081.7,
      "median": 3970,
      "p95": 57353,
      "p99": 59522.9
    },
    "rps": {
      "count": 17999,
      "mean": 49.99
    },
    "scenarioDuration": {
      "min": 105.4,
      "max": 60082.9,
      "median": 3971.1,
      "p95": 57354.8,
      "p99": 59524.8
    },
    "scenarioCounts": {
      "0": 17999
    },
    "errors": {
      "ESOCKETTIMEDOUT": 15016
    },
    "codes": {
      "200": 688,
      "500": 1,
      "502": 788,
      "503": 1506
    },
    "matches": 0,
    "customStats": {},
    "counters": {},
    "scenariosAvoided": 0,
    "phases": [
      {
        "name": "p0",
        "arrivalRate": 60,
        "duration": 60
      },
      {
        "name": "p1",
        "duration": 60,
        "arrivalRate": 60,
        "rampTo": 60
      },
      {
        "name": "p2",
        "duration": 180,
        "arrivalRate": 60
      }
    ]
  },
  "intermediate": [
    {
      "timestamp": "2020-07-14T16:26:53.678Z",
      "scenariosCreated": 599,
      "scenariosCompleted": 78,
      "requestsCompleted": 79,
      "latency": {
        "min": 105.2,
        "max": 8500.1,
        "median": 2255.5,
        "p95": 6988.8,
        "p99": 8474.6
      },
      "rps": {
        "count": 599,
        "mean": 60.2
      },
      "scenarioDuration": {
        "min": 106.6,
        "max": 8886.4,
        "median": 2288.5,
        "p95": 7022.4,
        "p99": 8778.9
      },
      "scenarioCounts": {
        "0": 599
      },
      "errors": {},
      "codes": {
        "200": 22,
        "503": 57
      },
      "matches": 0,
      "latencies": [
        3345171318,
        3197168387,
        2132775311,
        156756464,
        164249883,
        3916382640,
        150328219,
        4033541089,
        193458734,
        138158083,
        173829618,
        118541477,
        119918065,
        119579233,
        164532583,
        3966802141,
        4077803328,
        4571225346,
        4258338183,
        4349926305,
        2255481623,
        2290695684,
        186992711,
        154568303,
        129043125,
        137414617,
        115423796,
        110748419,
        207911230,
        192391627,
        163076616,
        113667670,
        3943030625,
        4293245743,
        2595307762,
        3695363015,
        2315011933,
        1552454906,
        4403654336,
        180760532,
        3820696595,
        4150432334,
        3389793973,
        4399627604,
        8412053380,
        8500143176,
        3924074478,
        6637271813,
        6571161968,
        8004593224,
        5905225096,
        5672372905,
        5205968623,
        4006240934,
        2506559977,
        406852496,
        5638836504,
        5341333408,
        1274790965,
        2642243676,
        7276471082,
        2961844148,
        302976085,
        236685892,
        137020364,
        170938597,
        205938685,
        272868853,
        117827086,
        105176583,
        3832950235,
        3772593301,
        3761440762,
        831362757,
        864817731,
        799047955,
        699271749,
        899479863,
        528540947
      ],
      "customStats": {},
      "counters": {},
      "concurrency": 521,
      "pendingRequests": 520,
      "scenariosAvoided": 0
    },
    {
      "timestamp": "2020-07-14T16:27:03.678Z",
      "scenariosCreated": 600,
      "scenariosCompleted": 225,
      "requestsCompleted": 224,
      "latency": {
        "min": 106.4,
        "max": 10506,
        "median": 380.3,
        "p95": 7118.2,
        "p99": 9928.3
      },
      "rps": {
        "count": 600,
        "mean": 60
      },
      "scenarioDuration": {
        "min": 107.9,
        "max": 10508,
        "median": 384,
        "p95": 7091.5,
        "p99": 9923.9
      },
      "scenarioCounts": {
        "0": 600
      },
      "errors": {},
      "codes": {
        "200": 22,
        "503": 202
      },
      "matches": 0,
      "latencies": [
        3293569583,
        2523993693,
        1925792367,
        3917668542,
        111255433,
        189279215,
        127350382,
        167046909,
        122739335,
        229316435,
        1140762083,
        1075114055,
        1011067233,
        950473319,
        1250646871,
        489026159,
        592238932,
        561406296,
        106389996,
        116442975,
        8945008286,
        9042004330,
        3806402847,
        10506010225,
        1007051242,
        4907046694,
        3007374931,
        2907114456,
        1074528719,
        4341385593,
        4942646251,
        9711497709,
        8312854246,
        9745720329,
        7514701657,
        6948276876,
        10448108987,
        8250130450,
        112055194,
        110628848,
        146465549,
        121806460,
        5338786308,
        117766644,
        119444113,
        465557834,
        136391725,
        110139090,
        145881551,
        678692524,
        612434163,
        213777549,
        648359557,
        186331856,
        169947118,
        137130357,
        4137364988,
        188448993,
        117775957,
        5859124039,
        117438763,
        188604080,
        156767941,
        123781672,
        221084308,
        136863083,
        3763390055,
        3675176066,
        3050024545,
        508030329,
        544428556,
        1116599018,
        1807510641,
        2952244004,
        505678920,
        605434589,
        473950514,
        323256872,
        150197943,
        186279906,
        151500309,
        175645856,
        207965503,
        3938609588,
        265631258,
        200059426,
        136145320,
        177439393,
        144695799,
        107161924,
        134442447,
        8395381338,
        182158746,
        6274272219,
        210590653,
        4134612333,
        2114176080,
        281069081,
        2048212483,
        1521128897,
        2192623788,
        2028902494,
        146648968,
        171685837,
        175730032,
        155115810,
        131182262,
        125946860,
        106561016,
        182431782,
        603935198,
        242743702,
        576487134,
        510120533,
        377057451,
        444215708,
        352830359,
        547419716,
        638921243,
        674019413,
        2047415914,
        112811393,
        107173829,
        112748318,
        111321840,
        4066378946,
        126232587,
        119806091,
        114027958,
        109999718,
        167359045,
        146936749,
        2235383016,
        2038463812,
        2505423497,
        1939244448,
        128052901,
        142780365,
        190237375,
        165564047,
        151204057,
        143778464,
        138745734,
        210381522,
        169018362,
        488027017,
        172047008,
        121892904,
        175036593,
        311572004,
        239262580,
        228818372,
        150044130,
        218086437,
        137658905,
        6662954375,
        140017590,
        119977829,
        414982244,
        3941447739,
        1972492121,
        2275103981,
        127509813,
        341916436,
        275617595,
        243003326,
        411247912,
        378210636,
        178420623,
        312439569,
        235711399,
        369276351,
        303283086,
        213797947,
        881924734,
        1417673673,
        183576168,
        283659846,
        317425475,
        220166863,
        139466370,
        197324060,
        204639369,
        172075741,
        3838164391,
        341484110,
        382486295,
        400823119,
        446867515,
        211556673,
        252326051,
        451974441,
        354147811,
        525662058,
        993102333,
        4925854822,
        1563450565,
        5827608961,
        288342959,
        322394248,
        393311328,
        2362163890,
        2929363630,
        2496362690,
        2763249274,
        2296777307,
        2698580891,
        6556570747,
        126958125,
        687880763,
        622701100,
        660654830,
        728969475,
        6780426171,
        747701783,
        677113899,
        715127376,
        648651819,
        782485840,
        883188273,
        8087226278,
        5125547668,
        2236509173,
        1847120978
      ],
      "customStats": {},
      "counters": {},
      "concurrency": 896,
      "pendingRequests": 896,
      "scenariosAvoided": 0
    },
    {
      "timestamp": "2020-07-14T16:27:13.677Z",
      "scenariosCreated": 600,
      "scenariosCompleted": 94,
      "requestsCompleted": 94,
      "latency": {
        "min": 110.5,
        "max": 29619.4,
        "median": 1456.5,
        "p95": 27869.2,
        "p99": 29337.7
      },
      "rps": {
        "count": 600,
        "mean": 60
      },
      "scenarioDuration": {
        "min": 111.9,
        "max": 29622.3,
        "median": 1458,
        "p95": 27877.8,
        "p99": 29340.2
      },
      "scenarioCounts": {
        "0": 600
      },
      "errors": {},
      "codes": {
        "200": 33,
        "503": 61
      },
      "matches": 0,
      "latencies": [
        7245702747,
        20300460640,
        18957199626,
        6625204646,
        3921461868,
        2227234333,
        2704165582,
        5973071234,
        179779701,
        143332020,
        198943764,
        171650131,
        200168306,
        20843347535,
        445812387,
        1016818737,
        1795634942,
        123450283,
        21026947026,
        8683810383,
        468900383,
        436271413,
        403174525,
        8027279496,
        17164543402,
        5397426170,
        1325321898,
        1025847597,
        5116492954,
        372599245,
        1587700105,
        695496582,
        562529761,
        761976391,
        669973706,
        565044011,
        466501191,
        766967849,
        667158259,
        535631658,
        6586254032,
        5875078558,
        22912495414,
        16494185323,
        24820574800,
        27240082445,
        19163483245,
        18025913438,
        4751922487,
        28026476987,
        24924867958,
        20252401833,
        9906640706,
        24504299490,
        533445802,
        9967898789,
        2375866396,
        3161406959,
        430112502,
        297450366,
        333311855,
        533511071,
        366816079,
        2098158230,
        2649836947,
        2483168474,
        2947885795,
        2417439016,
        2749958877,
        5473632309,
        138125739,
        28906416390,
        110457998,
        28979200906,
        240238717,
        505246482,
        5503707058,
        5103135432,
        28555984926,
        29619422924,
        495150281,
        529217556,
        571174722,
        837972286,
        805189302,
        742428958,
        709886250,
        611023418,
        778203424,
        646790882,
        250500504,
        670266295,
        604298517,
        639572907
      ],
      "customStats": {},
      "counters": {},
      "concurrency": 1402,
      "pendingRequests": 1402,
      "scenariosAvoided": 0
    },
    {
      "timestamp": "2020-07-14T16:27:23.677Z",
      "scenariosCreated": 600,
      "scenariosCompleted": 142,
      "requestsCompleted": 142,
      "latency": {
        "min": 108.2,
        "max": 38640.9,
        "median": 1294.8,
        "p95": 30540.2,
        "p99": 32838.2
      },
      "rps": {
        "count": 600,
        "mean": 60
      },
      "scenarioDuration": {
        "min": 109.5,
        "max": 38642.5,
        "median": 1296,
        "p95": 30541.9,
        "p99": 32839.8
      },
      "scenarioCounts": {
        "0": 600
      },
      "errors": {},
      "codes": {
        "200": 32,
        "503": 110
      },
      "matches": 0,
      "latencies": [
        2587274823,
        1956369193,
        29901779046,
        23073484662,
        578447892,
        545114992,
        614014001,
        648893882,
        623526311,
        825926303,
        792870486,
        3723111179,
        359115118,
        293950206,
        4720526644,
        378838766,
        345846766,
        30155239889,
        491789653,
        459430130,
        426364643,
        7236218769,
        31117634611,
        31289595706,
        21479752120,
        29649873113,
        32246087408,
        2222043395,
        2055841650,
        1022843632,
        1398183923,
        196265386,
        21226417311,
        32333633935,
        29528566885,
        2351826780,
        1696209188,
        1530689821,
        192967525,
        135578880,
        516204608,
        457739163,
        491489291,
        392910320,
        426574644,
        362076659,
        30023942187,
        6153602034,
        30092048482,
        21760075722,
        3757581984,
        26768280207,
        2448271488,
        2682061975,
        2515220071,
        2915328115,
        2717987265,
        1951540295,
        108232782,
        111699383,
        160668335,
        1012426137,
        1879295035,
        1646269301,
        1913549508,
        1081982040,
        1716724882,
        312238806,
        3217112096,
        955294553,
        171257598,
        2459069232,
        122462184,
        28722330237,
        158261739,
        1545016125,
        129929563,
        206349816,
        31301485924,
        151006012,
        117575423,
        204475291,
        174164876,
        5580386355,
        118557903,
        29827832975,
        393650431,
        327246748,
        294213465,
        228688201,
        7391391363,
        898324710,
        1286355408,
        2456387663,
        2526301334,
        1136389681,
        131129432,
        434817635,
        11644636671,
        344858750,
        124347112,
        31119349993,
        18751101853,
        3679704967,
        857113866,
        2365396170,
        2894796247,
        3016433411,
        378479037,
        312138952,
        319287720,
        432661318,
        200132607,
        368392197,
        38640911483,
        319774553,
        164094571,
        6132682988,
        1303193431,
        1412640761,
        2281943688,
        428459864,
        369759531,
        304280897,
        9516263014,
        601263412,
        1968906078,
        2035995740,
        2005322700,
        1072792425,
        2071791394,
        3005755568,
        2372545839,
        2539511650,
        1873110158,
        2208440904,
        124737979,
        113635386,
        29845646130,
        172345923,
        139289499,
        112034007
      ],
      "customStats": {},
      "counters": {},
      "concurrency": 1860,
      "pendingRequests": 1860,
      "scenariosAvoided": 0
    },
    {
      "timestamp": "2020-07-14T16:27:33.677Z",
      "scenariosCreated": 600,
      "scenariosCompleted": 179,
      "requestsCompleted": 179,
      "latency": {
        "min": 105.6,
        "max": 47074.7,
        "median": 1705.3,
        "p95": 42591.2,
        "p99": 44924.2
      },
      "rps": {
        "count": 600,
        "mean": 60
      },
      "scenarioDuration": {
        "min": 106.9,
        "max": 47076.3,
        "median": 1706.6,
        "p95": 42592.8,
        "p99": 44925.7
      },
      "scenarioCounts": {
        "0": 600
      },
      "errors": {},
      "codes": {
        "200": 52,
        "503": 127
      },
      "matches": 0,
      "latencies": [
        115514705,
        30507585313,
        33596649006,
        120167494,
        109233022,
        4009504244,
        143827126,
        119115012,
        155366570,
        227333898,
        31510569589,
        10796663573,
        10733095295,
        8900130084,
        2334293186,
        4301376917,
        8535226304,
        4939839598,
        18583237100,
        32362336701,
        2517863681,
        2584770855,
        3574489432,
        130225631,
        129585227,
        133159508,
        142397128,
        195718642,
        289368215,
        2184232729,
        2217825845,
        2286053140,
        2023160065,
        1790583578,
        1657740887,
        1157977676,
        1859785594,
        36414824490,
        1284386334,
        1694044677,
        33795403100,
        2201152152,
        1802478444,
        1904452675,
        2005979345,
        112716400,
        42286496321,
        117543605,
        126050772,
        6195198860,
        3717406733,
        3910716189,
        7052289037,
        43088228118,
        43233657415,
        39338485145,
        3742332198,
        2809266467,
        3577444692,
        148572996,
        107284611,
        120389947,
        106506600,
        143504783,
        117716121,
        114980760,
        1705283508,
        105617974,
        1672534255,
        1606028747,
        1739579620,
        1506662965,
        1574294090,
        1407811058,
        1640588065,
        123289710,
        108521058,
        114141162,
        30864551697,
        29966185428,
        27104714367,
        29738990975,
        14606768081,
        28108042969,
        8942906135,
        9043370104,
        109519546,
        143712699,
        1664803102,
        1665731999,
        23151467413,
        3029357530,
        1673706659,
        1377865875,
        135765250,
        130262436,
        10960096389,
        163033160,
        142274628,
        285338512,
        254157884,
        458187755,
        3408032116,
        2843127068,
        3443611936,
        3146837417,
        3247575426,
        6018652758,
        140582641,
        126729340,
        158820534,
        130105860,
        125372352,
        122174217,
        123919854,
        2598678004,
        2466759582,
        216881812,
        43427759867,
        3284821377,
        6195034085,
        43329707114,
        7628476367,
        45242624440,
        642739172,
        1454848397,
        1587567206,
        47074661610,
        2786047425,
        240843698,
        243865404,
        283612438,
        42189625685,
        30670259531,
        3423424297,
        670435708,
        637473263,
        605404285,
        1551326464,
        1718203709,
        3584981004,
        1546390243,
        4380785472,
        3949698622,
        162912233,
        195184902,
        168954467,
        43471862956,
        160361307,
        144682817,
        120422685,
        160711339,
        208096363,
        157196272,
        126838820,
        139707925,
        138060737,
        118519941,
        119657123,
        134968398,
        24232473911,
        28799942722,
        6334401113,
        30100188704,
        29867281602,
        29932891817,
        24602930434,
        10403744945,
        42840466073,
        152884496,
        153313612,
        2322782352,
        2618451952,
        175356280,
        275604638,
        159315486,
        44144525770,
        6628961417,
        7358976088
      ],
      "customStats": {},
      "counters": {},
      "concurrency": 2281,
      "pendingRequests": 2281,
      "scenariosAvoided": 0
    },
    {
      "timestamp": "2020-07-14T16:27:43.677Z",
      "scenariosCreated": 600,
      "scenariosCompleted": 162,
      "requestsCompleted": 162,
      "latency": {
        "min": 105.5,
        "max": 56650.3,
        "median": 2632.6,
        "p95": 43870.6,
        "p99": 55155.7
      },
      "rps": {
        "count": 600,
        "mean": 60
      },
      "scenarioDuration": {
        "min": 106.7,
        "max": 56652.6,
        "median": 2634.5,
        "p95": 43872.1,
        "p99": 55157.3
      },
      "scenarioCounts": {
        "0": 600
      },
      "errors": {},
      "codes": {
        "200": 46,
        "503": 116
      },
      "matches": 0,
      "latencies": [
        46536161824,
        4133028196,
        4233957767,
        5034288100,
        2633323896,
        4369133163,
        4335850153,
        42238848842,
        4717982051,
        527918335,
        1036642199,
        2631920975,
        343669626,
        319049234,
        288851634,
        40513484611,
        266527728,
        121477614,
        186418659,
        122634615,
        6335159359,
        121759229,
        46843010527,
        189361644,
        3776353059,
        3810104380,
        3743868413,
        4013037751,
        3913391729,
        130554637,
        201076205,
        176976434,
        39691191857,
        45500932618,
        37110540571,
        6663510094,
        3408341979,
        51711430617,
        24845191050,
        4193732630,
        4037024997,
        3637048752,
        129686376,
        121232712,
        118687367,
        4279322864,
        114239093,
        113355365,
        116633985,
        112418507,
        33495165310,
        185908655,
        153183161,
        126160630,
        29261614422,
        157080776,
        7814616797,
        134076773,
        6218110622,
        2190283017,
        2657660693,
        3424514800,
        4691521234,
        2626758148,
        3928591913,
        120385276,
        6291469978,
        3620816472,
        1832785469,
        3569921140,
        196332848,
        124684480,
        135202907,
        107903120,
        149784334,
        129931154,
        105738753,
        141623405,
        145895584,
        5216382293,
        217739123,
        190226265,
        133160902,
        4414337359,
        4869452534,
        3469822842,
        3969967858,
        4670454046,
        4637527625,
        3939296458,
        133202083,
        109414694,
        2529831470,
        3530101697,
        3663651723,
        2831685589,
        3005502614,
        194420362,
        128542124,
        162658170,
        105522503,
        20635499529,
        19602517692,
        23969602482,
        24136453087,
        23803573684,
        16305035985,
        23739927531,
        22573551909,
        4814372517,
        55625334686,
        27451398968,
        18093201630,
        43673489220,
        2034600574,
        2704981833,
        1206707246,
        2207567212,
        2479106737,
        110612504,
        145726587,
        2740760518,
        3688446141,
        2757518869,
        56650325614,
        132061362,
        172562010,
        124636654,
        148668042,
        116519796,
        156230469,
        345682639,
        317306736,
        290225230,
        44166155714,
        6750946707,
        266860006,
        300674422,
        889058611,
        1697853390,
        779507050,
        1388292760,
        1160157723,
        3061791036,
        3130892889,
        1968591927,
        303942415,
        270941107,
        4214095956,
        184217039,
        215575236,
        5139284770,
        3017691349,
        23097842216,
        9875223813,
        40625158163,
        49292841359,
        4068762609,
        643583251,
        1386689194,
        2475495941,
        2577000992
      ],
      "customStats": {},
      "counters": {},
      "concurrency": 2719,
      "pendingRequests": 2719,
      "scenariosAvoided": 0
    },
    {
      "timestamp": "2020-07-14T16:27:53.679Z",
      "scenariosCreated": 600,
      "scenariosCompleted": 105,
      "requestsCompleted": 105,
      "latency": {
        "min": 106.7,
        "max": 59524.9,
        "median": 235.4,
        "p95": 40400.5,
        "p99": 59089.3
      },
      "rps": {
        "count": 600,
        "mean": 60
      },
      "scenarioDuration": {
        "min": 111.1,
        "max": 59527,
        "median": 238.8,
        "p95": 40402.2,
        "p99": 59091.3
      },
      "scenarioCounts": {
        "0": 600
      },
      "errors": {
        "ESOCKETTIMEDOUT": 410
      },
      "codes": {
        "200": 27,
        "503": 78
      },
      "matches": 0,
      "latencies": [
        204288331,
        139988270,
        174050636,
        114815492,
        4493148383,
        30030033011,
        2329446619,
        1304953317,
        2148040785,
        2484037344,
        175613742,
        145073607,
        124008167,
        6266312513,
        21272475562,
        4738739107,
        240849505,
        58484684176,
        7360551735,
        4567200726,
        59524924715,
        38313810260,
        37848316743,
        56285808646,
        7522901681,
        1603282067,
        2067961034,
        3239522517,
        2173070427,
        181055035,
        150659101,
        119939560,
        120896709,
        106721703,
        190117299,
        227782490,
        153546036,
        6581267993,
        8209420383,
        4728692417,
        46660539284,
        6826953442,
        2038479790,
        1403670803,
        2305053282,
        3137878623,
        132696130,
        142592082,
        117363325,
        116611970,
        119968469,
        116473677,
        125417907,
        115949453,
        116286274,
        133433364,
        135035776,
        35095932394,
        235425434,
        201344820,
        535412652,
        634400836,
        606811427,
        1745029287,
        161562911,
        223790215,
        200655526,
        167013308,
        166945042,
        137404491,
        21437127717,
        195299434,
        228708289,
        168386967,
        157644907,
        126627859,
        188988679,
        162073587,
        137415298,
        133864410,
        121510913,
        108128176,
        162730862,
        6392634874,
        18662440749,
        58732952460,
        24779791882,
        5231330490,
        982769866,
        1381495409,
        3118547764,
        1757099775,
        24903756705,
        152536504,
        149119333,
        121363222,
        117454579,
        31619730594,
        2282702785,
        2184782587,
        1462083462,
        2585409446,
        169006836,
        137209994,
        110183283
      ],
      "customStats": {},
      "counters": {},
      "concurrency": 2804,
      "pendingRequests": 3214,
      "scenariosAvoided": 0
    },
    {
      "timestamp": "2020-07-14T16:28:03.678Z",
      "scenariosCreated": 600,
      "scenariosCompleted": 81,
      "requestsCompleted": 81,
      "latency": {
        "min": 116,
        "max": 58549.4,
        "median": 438.7,
        "p95": 27550.2,
        "p99": 51740.8
      },
      "rps": {
        "count": 600,
        "mean": 60.06
      },
      "scenarioDuration": {
        "min": 119.5,
        "max": 58551.3,
        "median": 445.8,
        "p95": 27552.1,
        "p99": 51742.6
      },
      "scenarioCounts": {
        "0": 600
      },
      "errors": {
        "ESOCKETTIMEDOUT": 380
      },
      "codes": {
        "200": 16,
        "503": 65
      },
      "matches": 0,
      "latencies": [
        384559325,
        31405329224,
        2917006138,
        1319206623,
        1094445654,
        192383214,
        131565356,
        118559106,
        122507535,
        133973209,
        127717085,
        136556556,
        121510049,
        115993804,
        118830512,
        122284754,
        633017509,
        116171396,
        2220549346,
        2122946626,
        1855955469,
        174969093,
        175221893,
        58549362846,
        171651333,
        205755098,
        121028453,
        192462013,
        233582527,
        265182900,
        189702635,
        7044174652,
        22570976908,
        6578706721,
        4975668988,
        24395994290,
        6497807926,
        20378871360,
        22839316909,
        2165948822,
        2027137185,
        2430513947,
        2366751212,
        36586304395,
        3588920898,
        12251551491,
        13619524065,
        13524179922,
        4556928095,
        11060557220,
        170031184,
        139497999,
        129649900,
        116893204,
        277570445,
        254420233,
        256815214,
        31750061722,
        470405477,
        365398634,
        436049965,
        438720679,
        281624789,
        1378673553,
        6348022717,
        6269746416,
        2068492408,
        1872026927,
        379813012,
        217174162,
        185110857,
        129721381,
        930368499,
        1524406338,
        1734012375,
        168656104,
        136742803,
        128167083,
        23707412839,
        296314824,
        18653442690
      ],
      "customStats": {},
      "counters": {},
      "concurrency": 2943,
      "pendingRequests": 3733,
      "scenariosAvoided": 0
    },
    {
      "timestamp": "2020-07-14T16:28:13.677Z",
      "scenariosCreated": 600,
      "scenariosCompleted": 81,
      "requestsCompleted": 81,
      "latency": {
        "min": 110.5,
        "max": 59502.3,
        "median": 941.5,
        "p95": 39579.1,
        "p99": 56494
      },
      "rps": {
        "count": 600,
        "mean": 60.06
      },
      "scenarioDuration": {
        "min": 115.9,
        "max": 59504,
        "median": 946,
        "p95": 39580.7,
        "p99": 56495.7
      },
      "scenarioCounts": {
        "0": 600
      },
      "errors": {
        "ESOCKETTIMEDOUT": 511
      },
      "codes": {
        "200": 17,
        "503": 64
      },
      "matches": 0,
      "latencies": [
        1012792433,
        1281274615,
        1145494857,
        155603870,
        29660100569,
        224127436,
        124179625,
        167289320,
        137209153,
        25765584953,
        4469352108,
        45254005039,
        59502341269,
        1978669879,
        2083778861,
        2485514075,
        5284658014,
        36755611058,
        1231535464,
        1935505731,
        2134645979,
        1975305345,
        12678846566,
        5751253963,
        1299490247,
        1697465942,
        1853693960,
        906299141,
        376460326,
        43030069462,
        28276340233,
        6202317496,
        1539715253,
        1299748173,
        1901054183,
        1768994212,
        15261856226,
        15582073818,
        15692438437,
        16857098790,
        17126292505,
        15986706746,
        552747391,
        387570163,
        521745482,
        235846350,
        271196256,
        238366434,
        177865470,
        144475426,
        632036402,
        178747439,
        838092455,
        906587140,
        873778520,
        941527654,
        525578594,
        295727946,
        274524036,
        147697796,
        209934145,
        116212802,
        49798000087,
        135358432,
        168686872,
        169484546,
        238859259,
        6240470494,
        447343974,
        384173423,
        484514590,
        317159752,
        352400376,
        194722757,
        136083812,
        173674231,
        110513238,
        17435192065,
        14621571451,
        5389375439,
        213712038
      ],
      "customStats": {},
      "counters": {},
      "concurrency": 2951,
      "pendingRequests": 4252,
      "scenariosAvoided": 0
    },
    {
      "timestamp": "2020-07-14T16:28:23.680Z",
      "scenariosCreated": 600,
      "scenariosCompleted": 114,
      "requestsCompleted": 114,
      "latency": {
        "min": 108.1,
        "max": 58515.8,
        "median": 214.9,
        "p95": 43509.4,
        "p99": 56279.9
      },
      "rps": {
        "count": 600,
        "mean": 60
      },
      "scenarioDuration": {
        "min": 114,
        "max": 58517.5,
        "median": 222.1,
        "p95": 43510.9,
        "p99": 56281.6
      },
      "scenarioCounts": {
        "0": 600
      },
      "errors": {
        "ESOCKETTIMEDOUT": 450
      },
      "codes": {
        "200": 14,
        "503": 100
      },
      "matches": 0,
      "latencies": [
        404953225,
        503462810,
        272163417,
        406753068,
        476074261,
        212367390,
        175751327,
        12374800507,
        199189343,
        175023199,
        274338120,
        168460069,
        135131123,
        115772365,
        41437632572,
        122534961,
        190056011,
        158312563,
        189570020,
        160847806,
        124022933,
        246024658,
        217370234,
        182873499,
        152822392,
        126113441,
        114879358,
        54924728094,
        419156439,
        53007391523,
        387429104,
        354661625,
        255871993,
        189659874,
        158854380,
        5840432017,
        147483202,
        183339896,
        110713668,
        122582059,
        108090776,
        713881335,
        3448055520,
        2247726751,
        2055896067,
        119852578,
        177232999,
        119839365,
        180142924,
        163536576,
        201984422,
        179302684,
        144268960,
        147635334,
        156199201,
        124690654,
        110379712,
        43870263557,
        158295474,
        172858611,
        1282790264,
        755707033,
        2158268025,
        3225965379,
        200849038,
        163169840,
        157315673,
        23386001122,
        217394328,
        283295375,
        153777116,
        164877228,
        127268518,
        116486635,
        123643398,
        121912408,
        362651040,
        54444419671,
        55022202514,
        1454112944,
        1589303385,
        2454653901,
        2669852599,
        2273988878,
        58515799497,
        5946096811,
        1462932690,
        2432510757,
        1201902734,
        1633148445,
        42065743139,
        128228115,
        184302102,
        155592415,
        132723839,
        177716888,
        133426361,
        131293916,
        122797289,
        1540506842,
        1942389901,
        2184429553,
        2548934061,
        2488074199,
        2252707284,
        1521190741,
        5737007801,
        6177310420,
        1755914678,
        2087416007,
        1921240162,
        2023414075,
        150759532,
        120386631
      ],
      "customStats": {},
      "counters": {},
      "concurrency": 2987,
      "pendingRequests": 4738,
      "scenariosAvoided": 0
    },
    {
      "timestamp": "2020-07-14T16:28:33.679Z",
      "scenariosCreated": 600,
      "scenariosCompleted": 69,
      "requestsCompleted": 69,
      "latency": {
        "min": 123.1,
        "max": 59444.8,
        "median": 1363.8,
        "p95": 57208.6,
        "p99": 59041.6
      },
      "rps": {
        "count": 600,
        "mean": 60.06
      },
      "scenarioDuration": {
        "min": 128.6,
        "max": 59446.5,
        "median": 1368.1,
        "p95": 57210.1,
        "p99": 59043.2
      },
      "scenarioCounts": {
        "0": 600
      },
      "errors": {
        "ESOCKETTIMEDOUT": 437
      },
      "codes": {
        "200": 24,
        "503": 45
      },
      "matches": 0,
      "latencies": [
        150788639,
        183327100,
        123126766,
        192827662,
        183541098,
        216672366,
        6723209346,
        41894023222,
        5426176286,
        1828032941,
        1363770099,
        1300656306,
        1532570853,
        606964947,
        384963729,
        417064344,
        25220281412,
        718421576,
        1332503922,
        2367315411,
        769618072,
        572332022,
        372248782,
        508011672,
        1275773168,
        874538295,
        5598543076,
        37366328864,
        5052942688,
        24407695418,
        8534720819,
        1017561859,
        1624125813,
        1227936624,
        1333090649,
        1535126730,
        201138661,
        271775518,
        45842433748,
        277912183,
        244689022,
        233259192,
        5810605075,
        57204276480,
        50975757488,
        633971181,
        537172996,
        1471943280,
        1406453173,
        50912271032,
        494785254,
        363068407,
        464901394,
        59444821709,
        56250667203,
        56317134861,
        55085089617,
        54488602416,
        57322439993,
        57289780720,
        4162658684,
        5188230120,
        820915149,
        694971879,
        1761028129,
        2060048499,
        1729267566,
        28631779939,
        1103217374
      ],
      "customStats": {},
      "counters": {},
      "concurrency": 3081,
      "pendingRequests": 5269,
      "scenariosAvoided": 0
    },
    {
      "timestamp": "2020-07-14T16:28:43.678Z",
      "scenariosCreated": 600,
      "scenariosCompleted": 9,
      "requestsCompleted": 9,
      "latency": {
        "min": 4468.9,
        "max": 56314,
        "median": 10877,
        "p95": 56314,
        "p99": 56314
      },
      "rps": {
        "count": 600,
        "mean": 60.06
      },
      "scenarioDuration": {
        "min": 4472.6,
        "max": 56315.6,
        "median": 10881.5,
        "p95": 56315.6,
        "p99": 56315.6
      },
      "scenarioCounts": {
        "0": 600
      },
      "errors": {
        "ESOCKETTIMEDOUT": 458
      },
      "codes": {
        "200": 9
      },
      "matches": 0,
      "latencies": [
        9108128871,
        6727410895,
        5477569738,
        28023354751,
        56314018379,
        4468926931,
        47350158962,
        34167428344,
        10876986329
      ],
      "customStats": {},
      "counters": {},
      "concurrency": 3214,
      "pendingRequests": 5860,
      "scenariosAvoided": 0
    },
    {
      "timestamp": "2020-07-14T16:28:53.676Z",
      "scenariosCreated": 599,
      "scenariosCompleted": 8,
      "requestsCompleted": 8,
      "latency": {
        "min": 29072.4,
        "max": 58700.2,
        "median": 46338.3,
        "p95": 58700.2,
        "p99": 58700.2
      },
      "rps": {
        "count": 599,
        "mean": 60.08
      },
      "scenarioDuration": {
        "min": 29076.2,
        "max": 58704.6,
        "median": 46342.8,
        "p95": 58704.6,
        "p99": 58704.6
      },
      "scenarioCounts": {
        "0": 599
      },
      "errors": {
        "ESOCKETTIMEDOUT": 508
      },
      "codes": {
        "200": 8
      },
      "matches": 0,
      "latencies": [
        54335238802,
        49050187968,
        58700172194,
        53335519972,
        37963820110,
        30187579963,
        29072411712,
        43626368867
      ],
      "customStats": {},
      "counters": {},
      "concurrency": 3297,
      "pendingRequests": 6451,
      "scenariosAvoided": 0
    },
    {
      "timestamp": "2020-07-14T16:29:03.675Z",
      "scenariosCreated": 600,
      "scenariosCompleted": 51,
      "requestsCompleted": 51,
      "latency": {
        "min": 106.3,
        "max": 54092,
        "median": 402.1,
        "p95": 40679.5,
        "p99": 53988.2
      },
      "rps": {
        "count": 600,
        "mean": 60.06
      },
      "scenarioDuration": {
        "min": 108.2,
        "max": 54097.5,
        "median": 403.7,
        "p95": 40683.6,
        "p99": 53993.7
      },
      "scenarioCounts": {
        "0": 600
      },
      "errors": {
        "ESOCKETTIMEDOUT": 518
      },
      "codes": {
        "200": 8,
        "503": 43
      },
      "matches": 0,
      "latencies": [
        54091950429,
        40486840140,
        28121559130,
        34177769043,
        1657277914,
        1433537889,
        1766824001,
        1634198818,
        3301062326,
        736353017,
        2070299232,
        2107952798,
        128697384,
        110355556,
        132051460,
        110563603,
        134030613,
        34953809011,
        135013375,
        137554242,
        106321117,
        107073028,
        133312279,
        116572806,
        32510188314,
        129620542,
        115526893,
        43714591449,
        110933354,
        199513164,
        184402488,
        122961395,
        137488314,
        207280453,
        40689679606,
        402050190,
        450027126,
        1363929409,
        3708714676,
        4642384534,
        3875939736,
        4044026532,
        3744243795,
        3811135422,
        3478973413,
        214383741,
        169309149,
        111053905,
        121994845,
        108266436,
        110965484
      ],
      "customStats": {},
      "counters": {},
      "concurrency": 3328,
      "pendingRequests": 7000,
      "scenariosAvoided": 0
    },
    {
      "timestamp": "2020-07-14T16:29:13.675Z",
      "scenariosCreated": 600,
      "scenariosCompleted": 34,
      "requestsCompleted": 34,
      "latency": {
        "min": 2950.2,
        "max": 57680.2,
        "median": 21822.2,
        "p95": 56393.8,
        "p99": 57680.2
      },
      "rps": {
        "count": 600,
        "mean": 60.06
      },
      "scenarioDuration": {
        "min": 2951.5,
        "max": 57685,
        "median": 21823.8,
        "p95": 56398.1,
        "p99": 57685
      },
      "scenarioCounts": {
        "0": 600
      },
      "errors": {
        "ESOCKETTIMEDOUT": 527
      },
      "codes": {
        "200": 34
      },
      "matches": 0,
      "latencies": [
        57680217064,
        41445897023,
        56712630029,
        47746015907,
        41247374596,
        33146514242,
        22916147052,
        24913077771,
        27281159362,
        21651130238,
        21081537182,
        17930746978,
        11431102509,
        16831338178,
        9798421457,
        10034084775,
        2950182607,
        49305041416,
        45037952328,
        26472892441,
        47139655568,
        24880476175,
        22227097077,
        21993329965,
        15161684323,
        13595234322,
        19530556894,
        16997682431,
        3172672585,
        5550825067,
        2978866344,
        8247838066,
        8061328651,
        55118369577
      ],
      "customStats": {},
      "counters": {},
      "concurrency": 3367,
      "pendingRequests": 7566,
      "scenariosAvoided": 0
    },
    {
      "timestamp": "2020-07-14T16:29:23.677Z",
      "scenariosCreated": 600,
      "scenariosCompleted": 1,
      "requestsCompleted": 1,
      "latency": {
        "min": 46522.7,
        "max": 46522.7,
        "median": 46522.7,
        "p95": 46522.7,
        "p99": 46522.7
      },
      "rps": {
        "count": 600,
        "mean": 60.06
      },
      "scenarioDuration": {
        "min": 46526.8,
        "max": 46526.8,
        "median": 46526.8,
        "p95": 46526.8,
        "p99": 46526.8
      },
      "scenarioCounts": {
        "0": 600
      },
      "errors": {
        "ESOCKETTIMEDOUT": 484
      },
      "codes": {
        "200": 1
      },
      "matches": 0,
      "latencies": [
        46522655714
      ],
      "customStats": {},
      "counters": {},
      "concurrency": 3482,
      "pendingRequests": 8165,
      "scenariosAvoided": 0
    },
    {
      "timestamp": "2020-07-14T16:29:33.675Z",
      "scenariosCreated": 600,
      "scenariosCompleted": 24,
      "requestsCompleted": 24,
      "latency": {
        "min": 3457.2,
        "max": 55474.3,
        "median": 35303.2,
        "p95": 53769.7,
        "p99": 55474.3
      },
      "rps": {
        "count": 600,
        "mean": 60.06
      },
      "scenarioDuration": {
        "min": 3458.4,
        "max": 55481.4,
        "median": 35304.5,
        "p95": 53773.7,
        "p99": 55481.4
      },
      "scenarioCounts": {
        "0": 600
      },
      "errors": {
        "ESOCKETTIMEDOUT": 544
      },
      "codes": {
        "200": 24
      },
      "matches": 0,
      "latencies": [
        55474276134,
        50945010654,
        41461531294,
        51079059120,
        28862333417,
        50013937824,
        30563157795,
        42697123394,
        44015340220,
        46166992128,
        42818324676,
        36118768297,
        31985629599,
        19919827005,
        23086438911,
        18720093639,
        11553893488,
        53039102326,
        10754436654,
        47771920937,
        34487642213,
        8825741989,
        25399097265,
        3457233675
      ],
      "customStats": {},
      "counters": {},
      "concurrency": 3514,
      "pendingRequests": 8741,
      "scenariosAvoided": 0
    },
    {
      "timestamp": "2020-07-14T16:29:43.675Z",
      "scenariosCreated": 600,
      "scenariosCompleted": 0,
      "requestsCompleted": 0,
      "latency": {
        "min": null,
        "max": null,
        "median": null,
        "p95": null,
        "p99": null
      },
      "rps": {
        "count": 600,
        "mean": 60.06
      },
      "scenarioDuration": {
        "min": null,
        "max": null,
        "median": null,
        "p95": null,
        "p99": null
      },
      "scenarioCounts": {
        "0": 600
      },
      "errors": {
        "ESOCKETTIMEDOUT": 586
      },
      "codes": {},
      "matches": 0,
      "latencies": [],
      "customStats": {},
      "counters": {},
      "concurrency": 3528,
      "pendingRequests": 9341,
      "scenariosAvoided": 0
    },
    {
      "timestamp": "2020-07-14T16:29:53.675Z",
      "scenariosCreated": 600,
      "scenariosCompleted": 1,
      "requestsCompleted": 1,
      "latency": {
        "min": 41121.7,
        "max": 41121.7,
        "median": 41121.7,
        "p95": 41121.7,
        "p99": 41121.7
      },
      "rps": {
        "count": 600,
        "mean": 60.06
      },
      "scenarioDuration": {
        "min": 41123,
        "max": 41123,
        "median": 41123,
        "p95": 41123,
        "p99": 41123
      },
      "scenarioCounts": {
        "0": 600
      },
      "errors": {
        "ESOCKETTIMEDOUT": 587
      },
      "codes": {
        "200": 1
      },
      "matches": 0,
      "latencies": [
        41121668733
      ],
      "customStats": {},
      "counters": {},
      "concurrency": 3540,
      "pendingRequests": 9940,
      "scenariosAvoided": 0
    },
    {
      "timestamp": "2020-07-14T16:30:03.677Z",
      "scenariosCreated": 600,
      "scenariosCompleted": 9,
      "requestsCompleted": 9,
      "latency": {
        "min": 25854.9,
        "max": 28048.8,
        "median": 27921.9,
        "p95": 28048.8,
        "p99": 28048.8
      },
      "rps": {
        "count": 600,
        "mean": 60
      },
      "scenarioDuration": {
        "min": 25856.2,
        "max": 28050,
        "median": 27923.1,
        "p95": 28050,
        "p99": 28050
      },
      "scenarioCounts": {
        "0": 600
      },
      "errors": {
        "ESOCKETTIMEDOUT": 547
      },
      "codes": {
        "200": 9
      },
      "matches": 0,
      "latencies": [
        28048759078,
        27948217610,
        25954509359,
        25854899844,
        27921878990,
        28021991006,
        27989210103,
        25923905757,
        25890797079
      ],
      "customStats": {},
      "counters": {},
      "concurrency": 3584,
      "pendingRequests": 10531,
      "scenariosAvoided": 0
    },
    {
      "timestamp": "2020-07-14T16:30:13.676Z",
      "scenariosCreated": 600,
      "scenariosCompleted": 18,
      "requestsCompleted": 18,
      "latency": {
        "min": 106.4,
        "max": 59653.3,
        "median": 1029,
        "p95": 36966,
        "p99": 59653.3
      },
      "rps": {
        "count": 600,
        "mean": 60
      },
      "scenarioDuration": {
        "min": 107.9,
        "max": 59654.6,
        "median": 1030.7,
        "p95": 36967.3,
        "p99": 59654.6
      },
      "scenarioCounts": {
        "0": 600
      },
      "errors": {
        "ESOCKETTIMEDOUT": 591
      },
      "codes": {
        "200": 1,
        "503": 17
      },
      "matches": 0,
      "latencies": [
        59653259182,
        772332917,
        998886028,
        1600601768,
        1800833530,
        2935194747,
        868798861,
        836380422,
        2020881678,
        173807659,
        141706751,
        114839145,
        106440674,
        266808576,
        1342397837,
        1444365768,
        1247598514,
        1059121735
      ],
      "customStats": {},
      "counters": {},
      "concurrency": 3575,
      "pendingRequests": 11113,
      "scenariosAvoided": 0
    },
    {
      "timestamp": "2020-07-14T16:30:23.676Z",
      "scenariosCreated": 600,
      "scenariosCompleted": 37,
      "requestsCompleted": 37,
      "latency": {
        "min": 269.2,
        "max": 53041.5,
        "median": 4958.6,
        "p95": 49655.1,
        "p99": 53041.5
      },
      "rps": {
        "count": 600,
        "mean": 60
      },
      "scenarioDuration": {
        "min": 270.4,
        "max": 53042.7,
        "median": 4959.8,
        "p95": 49656.3,
        "p99": 53042.7
      },
      "scenarioCounts": {
        "0": 600
      },
      "errors": {
        "ESOCKETTIMEDOUT": 596
      },
      "codes": {
        "200": 20,
        "503": 17
      },
      "matches": 0,
      "latencies": [
        2780063240,
        2518783597,
        2619735230,
        2599757463,
        4958590220,
        700816111,
        799822650,
        566877524,
        1100680571,
        379551544,
        947126260,
        414118389,
        357295095,
        326748465,
        300514527,
        269243811,
        806701343,
        989908733,
        5183153376,
        29614506472,
        24317635245,
        46466974634,
        40700849677,
        19485277840,
        9519358201,
        7091188370,
        12826014120,
        15827671230,
        29732064100,
        25468066354,
        29673628418,
        5182086138,
        51371754983,
        53041490503,
        3432161259,
        9246652809,
        5469183903
      ],
      "customStats": {},
      "counters": {},
      "concurrency": 3542,
      "pendingRequests": 11676,
      "scenariosAvoided": 0
    },
    {
      "timestamp": "2020-07-14T16:30:33.676Z",
      "scenariosCreated": 600,
      "scenariosCompleted": 0,
      "requestsCompleted": 0,
      "latency": {
        "min": null,
        "max": null,
        "median": null,
        "p95": null,
        "p99": null
      },
      "rps": {
        "count": 600,
        "mean": 60
      },
      "scenarioDuration": {
        "min": null,
        "max": null,
        "median": null,
        "p95": null,
        "p99": null
      },
      "scenarioCounts": {
        "0": 600
      },
      "errors": {
        "ESOCKETTIMEDOUT": 588
      },
      "codes": {},
      "matches": 0,
      "latencies": [],
      "customStats": {},
      "counters": {},
      "concurrency": 3554,
      "pendingRequests": 12276,
      "scenariosAvoided": 0
    },
    {
      "timestamp": "2020-07-14T16:30:43.676Z",
      "scenariosCreated": 600,
      "scenariosCompleted": 0,
      "requestsCompleted": 0,
      "latency": {
        "min": null,
        "max": null,
        "median": null,
        "p95": null,
        "p99": null
      },
      "rps": {
        "count": 600,
        "mean": 60
      },
      "scenarioDuration": {
        "min": null,
        "max": null,
        "median": null,
        "p95": null,
        "p99": null
      },
      "scenarioCounts": {
        "0": 600
      },
      "errors": {
        "ESOCKETTIMEDOUT": 599
      },
      "codes": {},
      "matches": 0,
      "latencies": [],
      "customStats": {},
      "counters": {},
      "concurrency": 3555,
      "pendingRequests": 12876,
      "scenariosAvoided": 0
    },
    {
      "timestamp": "2020-07-14T16:30:53.676Z",
      "scenariosCreated": 600,
      "scenariosCompleted": 2,
      "requestsCompleted": 2,
      "latency": {
        "min": 33483.1,
        "max": 39478.8,
        "median": 36481,
        "p95": 39478.8,
        "p99": 39478.8
      },
      "rps": {
        "count": 600,
        "mean": 60
      },
      "scenarioDuration": {
        "min": 33485.2,
        "max": 39480.2,
        "median": 36482.7,
        "p95": 39480.2,
        "p99": 39480.2
      },
      "scenarioCounts": {
        "0": 600
      },
      "errors": {
        "ESOCKETTIMEDOUT": 595
      },
      "codes": {
        "200": 2
      },
      "matches": 0,
      "latencies": [
        33483122947,
        39478836814
      ],
      "customStats": {},
      "counters": {},
      "concurrency": 3558,
      "pendingRequests": 13474,
      "scenariosAvoided": 0
    },
    {
      "timestamp": "2020-07-14T16:31:03.676Z",
      "scenariosCreated": 600,
      "scenariosCompleted": 2,
      "requestsCompleted": 2,
      "latency": {
        "min": 58748.1,
        "max": 60081.7,
        "median": 59414.9,
        "p95": 60081.7,
        "p99": 60081.7
      },
      "rps": {
        "count": 600,
        "mean": 60
      },
      "scenarioDuration": {
        "min": 58749.3,
        "max": 60082.9,
        "median": 59416.1,
        "p95": 60082.9,
        "p99": 60082.9
      },
      "scenarioCounts": {
        "0": 600
      },
      "errors": {
        "ESOCKETTIMEDOUT": 596
      },
      "codes": {
        "200": 2
      },
      "matches": 0,
      "latencies": [
        58748072428,
        60081737520
      ],
      "customStats": {},
      "counters": {},
      "concurrency": 3560,
      "pendingRequests": 14072,
      "scenariosAvoided": 0
    },
    {
      "timestamp": "2020-07-14T16:31:13.675Z",
      "scenariosCreated": 600,
      "scenariosCompleted": 26,
      "requestsCompleted": 26,
      "latency": {
        "min": 7685.4,
        "max": 57641.5,
        "median": 39954.8,
        "p95": 57608.3,
        "p99": 57641.5
      },
      "rps": {
        "count": 600,
        "mean": 60
      },
      "scenarioDuration": {
        "min": 7686.5,
        "max": 57642.7,
        "median": 39956,
        "p95": 57609.5,
        "p99": 57642.7
      },
      "scenarioCounts": {
        "0": 600
      },
      "errors": {
        "ESOCKETTIMEDOUT": 538
      },
      "codes": {
        "200": 26
      },
      "matches": 0,
      "latencies": [
        57599936828,
        51072725806,
        40506812566,
        34157354873,
        55007175490,
        32091974823,
        57641505775,
        46642364616,
        39976287346,
        47676403516,
        37044035675,
        33727772898,
        14166107629,
        8966139858,
        17900346803,
        48027649007,
        48798344537,
        47698483202,
        43099807272,
        39933409342,
        13651254631,
        35050530030,
        8251829173,
        7685388966,
        47100687632,
        39468502160
      ],
      "customStats": {},
      "counters": {},
      "concurrency": 3596,
      "pendingRequests": 14646,
      "scenariosAvoided": 0
    },
    {
      "timestamp": "2020-07-14T16:31:23.675Z",
      "scenariosCreated": 600,
      "scenariosCompleted": 17,
      "requestsCompleted": 17,
      "latency": {
        "min": 314.5,
        "max": 57841.9,
        "median": 6501,
        "p95": 57703,
        "p99": 57841.9
      },
      "rps": {
        "count": 600,
        "mean": 60
      },
      "scenarioDuration": {
        "min": 315.7,
        "max": 57843.1,
        "median": 6502.4,
        "p95": 57704.1,
        "p99": 57843.1
      },
      "scenarioCounts": {
        "0": 600
      },
      "errors": {
        "ESOCKETTIMEDOUT": 613
      },
      "codes": {
        "200": 10,
        "503": 7
      },
      "matches": 0,
      "latencies": [
        2847473730,
        6522919132,
        6501022524,
        9853651387,
        1305222262,
        314492555,
        661835079,
        2228753690,
        1095850797,
        1071702745,
        57841928630,
        44326160952,
        54808805593,
        57444874367,
        43707483448,
        1666585135,
        12605898565
      ],
      "customStats": {},
      "counters": {},
      "concurrency": 3566,
      "pendingRequests": 15229,
      "scenariosAvoided": 0
    },
    {
      "timestamp": "2020-07-14T16:31:33.675Z",
      "scenariosCreated": 600,
      "scenariosCompleted": 175,
      "requestsCompleted": 175,
      "latency": {
        "min": 104.4,
        "max": 57669.9,
        "median": 114.2,
        "p95": 14405.3,
        "p99": 56028.2
      },
      "rps": {
        "count": 600,
        "mean": 60
      },
      "scenarioDuration": {
        "min": 105.5,
        "max": 57671.1,
        "median": 115.7,
        "p95": 14406.4,
        "p99": 56029.5
      },
      "scenarioCounts": {
        "0": 600
      },
      "errors": {
        "ESOCKETTIMEDOUT": 585
      },
      "codes": {
        "200": 5,
        "502": 14,
        "503": 156
      },
      "matches": 0,
      "latencies": [
        108185180,
        4265684429,
        4399863891,
        24913197469,
        56336320250,
        57669924706,
        47320519384,
        55103713162,
        28954847686,
        20288776333,
        40589623439,
        15890832670,
        4350642447,
        2034104727,
        1801122438,
        2003355048,
        2336868805,
        1571194408,
        1512345508,
        1445912995,
        1713376453,
        1781272603,
        1881770922,
        721596644,
        356425137,
        1090919423,
        110668441,
        2184018622,
        2260513836,
        2294177575,
        2129893939,
        2230190858,
        116794520,
        113820207,
        132309123,
        125154542,
        131576568,
        120840083,
        117244638,
        112519718,
        107990197,
        109728578,
        123399072,
        112889279,
        148041482,
        119211143,
        138921292,
        113329729,
        142934167,
        118402851,
        115138859,
        107162677,
        153578376,
        188241676,
        121895502,
        109401422,
        107489888,
        106569459,
        8000688483,
        124772883,
        110680759,
        111941239,
        107376508,
        107657540,
        105709526,
        122460022,
        165529236,
        132555925,
        107519633,
        121764890,
        116579305,
        106443423,
        142306900,
        120957852,
        106121308,
        106944051,
        110141849,
        109428398,
        108216517,
        108939599,
        116485777,
        118441511,
        108832877,
        105272267,
        108648024,
        105108684,
        111372211,
        107172129,
        104664234,
        118366340,
        104413138,
        113271202,
        108332386,
        108102977,
        120569089,
        119139869,
        110198258,
        117554217,
        117582054,
        106338077,
        106702730,
        120182453,
        105803972,
        108316293,
        109417902,
        107867961,
        105457332,
        126390516,
        112123305,
        105850711,
        106740208,
        106852676,
        9948524611,
        111293945,
        108140577,
        118184963,
        118131815,
        116812440,
        115673688,
        117915499,
        105943310,
        107127074,
        107416546,
        108091405,
        124685214,
        106182739,
        107635442,
        117108876,
        117773251,
        110216159,
        106966973,
        105366548,
        106996695,
        120679789,
        105908642,
        105928727,
        110418369,
        117609396,
        108964681,
        105881987,
        118355312,
        121042354,
        105321604,
        107692161,
        118303888,
        110261422,
        119447140,
        118515066,
        106771386,
        110079903,
        119209747,
        107013191,
        107037027,
        106879673,
        120529597,
        113446541,
        110737638,
        105609978,
        105332570,
        119168520,
        113204729,
        106631358,
        106197255,
        120060612,
        107274014,
        118716644,
        107348195,
        120259987,
        114231562,
        111144235,
        107594902,
        107561429,
        118556359,
        105048488,
        111938951
      ],
      "customStats": {},
      "counters": {},
      "concurrency": 3406,
      "pendingRequests": 15654,
      "scenariosAvoided": 0
    },
    {
      "timestamp": "2020-07-14T16:31:43.676Z",
      "scenariosCreated": 600,
      "scenariosCompleted": 252,
      "requestsCompleted": 252,
      "latency": {
        "min": 104.2,
        "max": 59575.4,
        "median": 109,
        "p95": 8016,
        "p99": 52226.2
      },
      "rps": {
        "count": 600,
        "mean": 60
      },
      "scenarioDuration": {
        "min": 105.4,
        "max": 59576.7,
        "median": 110.2,
        "p95": 8017.1,
        "p99": 52227.4
      },
      "scenarioCounts": {
        "0": 600
      },
      "errors": {
        "ESOCKETTIMEDOUT": 588
      },
      "codes": {
        "200": 14,
        "503": 238
      },
      "matches": 0,
      "latencies": [
        118376848,
        107064707,
        106020220,
        107147065,
        106825636,
        119944864,
        105578631,
        106474710,
        104546594,
        111286867,
        106664544,
        117937991,
        106302486,
        109477855,
        120143435,
        119398931,
        118691267,
        125354511,
        114573325,
        107296650,
        106800010,
        106116749,
        122098167,
        112446486,
        107674249,
        104678924,
        111758609,
        107861717,
        107900634,
        113335114,
        109671658,
        109124141,
        106274271,
        109079712,
        116820549,
        117929227,
        113237956,
        105050475,
        106550560,
        111404367,
        105047093,
        118258557,
        107030074,
        109718505,
        117221606,
        108336469,
        108269266,
        109078134,
        106678309,
        106311474,
        107260013,
        108566320,
        106932017,
        120207302,
        106160595,
        107935049,
        118439204,
        107566074,
        107148637,
        111988872,
        106376492,
        105104850,
        118149748,
        107520701,
        117546346,
        107422350,
        106432552,
        121651899,
        106713242,
        111120472,
        106703768,
        122261182,
        109016170,
        106563169,
        107145941,
        111793327,
        108504773,
        111275909,
        106107826,
        108645923,
        105788322,
        117349893,
        107115923,
        113948000,
        109338461,
        107922835,
        116714542,
        107804571,
        117675975,
        118873806,
        109780988,
        107387965,
        106725704,
        109523931,
        105240099,
        111387503,
        107207316,
        106149081,
        104975682,
        118674098,
        121387757,
        108861542,
        117175833,
        110701480,
        116617273,
        120808597,
        105350266,
        106113436,
        117003193,
        107575685,
        109172825,
        110197119,
        111074518,
        118171489,
        118794463,
        107759258,
        106246279,
        105812337,
        109371888,
        110002876,
        109469763,
        107274101,
        117006347,
        107429123,
        106617807,
        106553178,
        122161977,
        126385413,
        111148781,
        108198689,
        108134121,
        106221879,
        59575362505,
        58042438873,
        52542801779,
        36710343314,
        33210860980,
        32844563019,
        20212107939,
        22747072828,
        28547422791,
        19314952842,
        17452620045,
        8555726186,
        121388431,
        115318532,
        105524612,
        106723386,
        106670273,
        107737210,
        109374100,
        107489565,
        106560705,
        115122676,
        140843114,
        111648801,
        106216818,
        110342464,
        107971799,
        109301661,
        106024433,
        117325539,
        107016607,
        119632552,
        116505840,
        109590941,
        109393979,
        106840848,
        107795805,
        104866421,
        108147032,
        119146042,
        107955454,
        116532316,
        106330888,
        120793853,
        108998920,
        108124113,
        107053375,
        121430618,
        104767271,
        116948604,
        105747273,
        106298747,
        109526754,
        111071736,
        117409373,
        120734543,
        104968147,
        106635323,
        108424216,
        107668401,
        117471958,
        111491707,
        109963141,
        117830308,
        105567110,
        106629704,
        107862856,
        104721119,
        104991917,
        117494487,
        122699244,
        121643122,
        118805289,
        107049712,
        106889451,
        110070862,
        107321546,
        106877226,
        106037066,
        118655392,
        3158211783,
        126557778,
        107709924,
        107880559,
        117384105,
        112022343,
        108443284,
        107108056,
        106919811,
        110410527,
        106814472,
        108197686,
        105384792,
        105101825,
        106496727,
        117096704,
        104249545,
        29705571033,
        118693051,
        110391121,
        121071120,
        105891213,
        107869883,
        118964021,
        118435953,
        106840824,
        111969166,
        107867049,
        112014236,
        106619545,
        107717705,
        132172562,
        105738688,
        105841930,
        105608213,
        115614265,
        113247657,
        119336308,
        108304774,
        109050754
      ],
      "customStats": {},
      "counters": {},
      "concurrency": 3166,
      "pendingRequests": 16002,
      "scenariosAvoided": 0
    },
    {
      "timestamp": "2020-07-14T16:31:53.678Z",
      "scenariosCreated": 1,
      "scenariosCompleted": 34,
      "requestsCompleted": 34,
      "latency": {
        "min": 109,
        "max": 59869.7,
        "median": 36351.1,
        "p95": 58549.3,
        "p99": 59869.7
      },
      "rps": {
        "count": 1,
        "mean": 0.1
      },
      "scenarioDuration": {
        "min": 110.4,
        "max": 59871.1,
        "median": 36352.4,
        "p95": 58550.7,
        "p99": 59871.1
      },
      "scenarioCounts": {
        "0": 1
      },
      "errors": {
        "ESOCKETTIMEDOUT": 593
      },
      "codes": {
        "200": 31,
        "503": 3
      },
      "matches": 0,
      "latencies": [
        116069052,
        117405664,
        108986328,
        58195562271,
        53563306243,
        20731953433,
        19999228620,
        21233154269,
        52265952744,
        25076227297,
        57208711354,
        54576443936,
        37811121219,
        35350799283,
        28685299155,
        35618583154,
        36453084117,
        23854675436,
        56368904225,
        59869667108,
        54670502564,
        58637691964,
        57040182755,
        36875432325,
        47342894160,
        28344187245,
        28811499984,
        32078694516,
        29612631784,
        44012609501,
        26480507344,
        44080527918,
        40048509308,
        36249019685
      ],
      "customStats": {},
      "counters": {},
      "concurrency": 2540,
      "pendingRequests": 15969,
      "scenariosAvoided": 0
    },
    {
      "timestamp": "2020-07-14T16:32:03.682Z",
      "scenariosCreated": 0,
      "scenariosCompleted": 337,
      "requestsCompleted": 337,
      "latency": {
        "min": 10784.7,
        "max": 60008.6,
        "median": 42792.1,
        "p95": 59170.2,
        "p99": 59724
      },
      "rps": {
        "count": 0,
        "mean": null
      },
      "scenarioDuration": {
        "min": 10786.1,
        "max": 60010.1,
        "median": 42793.5,
        "p95": 59171.9,
        "p99": 59726
      },
      "scenarioCounts": {},
      "errors": {
        "ESOCKETTIMEDOUT": 529
      },
      "codes": {
        "200": 59,
        "500": 1,
        "502": 277
      },
      "matches": 0,
      "latencies": [
        29409507473,
        37076584007,
        45109779682,
        54976153111,
        50109809646,
        45310161263,
        33477322192,
        14578100814,
        19644738558,
        34544315274,
        54676993686,
        11178767673,
        27511596625,
        19778271712,
        58443894678,
        53644174361,
        37278258493,
        25678855792,
        34511356073,
        37478650905,
        39345309172,
        55844660620,
        59144828479,
        40972698231,
        35107085219,
        50340476451,
        50241121246,
        39175387479,
        39742635847,
        35076754268,
        42843682764,
        55077102456,
        57810919587,
        41879187496,
        45879495492,
        34241538239,
        49275118314,
        35176385122,
        53209695807,
        44244111273,
        29111881746,
        50211565016,
        24713231934,
        30179743191,
        47413538522,
        38447562794,
        29748656152,
        21749599395,
        57748920973,
        10784724867,
        27751295999,
        20718848841,
        23852480301,
        45752173711,
        46685919941,
        55752865194,
        33344530938,
        27186779013,
        44387481892,
        19422395844,
        46555385657,
        55755233203,
        15224463665,
        21891527901,
        22292077548,
        47091609435,
        42859003894,
        26160122669,
        28693825012,
        24461304773,
        34061477847,
        32362045658,
        56994606094,
        18663649920,
        39697511968,
        47531057252,
        16232859538,
        51765301182,
        59698975729,
        24487354257,
        47020516555,
        36321015811,
        59687005869,
        52854047268,
        49787605335,
        13189226507,
        35055149762,
        22389053503,
        29689001662,
        23122610031,
        32322381153,
        36288596407,
        40989065651,
        59188072104,
        47488689099,
        52289072427,
        35856528832,
        57956710080,
        40357619047,
        15558682107,
        20925215925,
        32158298754,
        35239355415,
        55184190270,
        54785416185,
        51586114179,
        52520192495,
        43654476400,
        40488459284,
        33304293342,
        29272367176,
        33456525975,
        15974505366,
        19375078799,
        27242120193,
        19020716574,
        33087646580,
        57864184635,
        53898725173,
        56465889817,
        37233245513,
        30534782265,
        56600943112,
        58734638504,
        44602605979,
        58135675466,
        20704526137,
        53270652597,
        36005244908,
        58904812301,
        35906255055,
        55405997088,
        38047674456,
        37405605814,
        37806881057,
        33641043712,
        33775029634,
        34108933795,
        22343286142,
        33610726016,
        18645109153,
        30245351919,
        33312463444,
        31746235217,
        34994479518,
        57894520120,
        59561759222,
        32296955082,
        50030257485,
        23531892206,
        35865245678,
        58464996249,
        52832363245,
        55332965402,
        52933725582,
        40534728952,
        59568038925,
        35208800199,
        21810365002,
        29910688311,
        35511097939,
        34512160075,
        31072134758,
        32239992208,
        58573636200,
        40006240161,
        60008629676,
        40143436340,
        56809308042,
        53410840244,
        59444398356,
        36979156875,
        38579609539,
        44713348110,
        35781310115,
        37081945320,
        57347666710,
        29716689793,
        39871969919,
        44806065793,
        57872941686,
        47039965435,
        32108542988,
        53141503617,
        41342584170,
        33510287754,
        37277282891,
        54343869905,
        35506381203,
        27367675428,
        18953396016,
        42527800264,
        44562449205,
        54862283144,
        43329663511,
        42564141278,
        57664423259,
        59097536598,
        38133669637,
        59633545953,
        40101603574,
        17682116247,
        59611144707,
        58145180964,
        46313160802,
        52446859322,
        37714731720,
        57414525836,
        43282369741,
        55415696098,
        17784410201,
        41950571093,
        55850800045,
        34185471651,
        59364480208,
        39299614729,
        33833912748,
        36401145743,
        30135246610,
        55868180310,
        42336028171,
        59301790304,
        48169619387,
        54571034481,
        57938210891,
        47172550174,
        50539592471,
        59095836490,
        57563646037,
        35969498634,
        38670271154,
        55536795657,
        27571199170,
        24739215827,
        44604991958,
        40239300387,
        44640399236,
        39107875288,
        40574366569,
        40374986257,
        55501217195,
        54135559245,
        58202115426,
        59703723916,
        49607244942,
        46575793576,
        52109670372,
        44843249962,
        44377859578,
        41711889586,
        49745396745,
        42513025623,
        35813806855,
        37614509598,
        25725185412,
        50252677479,
        53786758964,
        42887965484,
        52954942818,
        55555465272,
        34823458770,
        55323142787,
        51390618447,
        36456575186,
        42792079136,
        52759031750,
        48226410039,
        59111249992,
        42546839306,
        49379467882,
        51614486800,
        55348334536,
        38516248342,
        56449474225,
        39217419691,
        39584545444,
        59183853825,
        59251091940,
        59718354502,
        59761951738,
        57163417680,
        44597981767,
        43998651966,
        46965171704,
        31900282330,
        37834147623,
        50467388322,
        45401664519,
        58402151695,
        40370316278,
        26806797967,
        56051707039,
        54119329672,
        55153438423,
        29354979499,
        57887949704,
        40621883089,
        58189231179,
        59888963456,
        37724398993,
        38525001185,
        38792283492,
        55458927556,
        36960156177,
        23668074458,
        40068761052,
        27019872091,
        23387010020,
        56488249729,
        55456159909,
        53289937563,
        35724953865,
        44725247517,
        44525885507,
        54192689055,
        40560452688,
        53227118066,
        47761323396,
        36529380301,
        56395922301,
        38430427410,
        38080375639,
        44547785661,
        44781775556,
        57281886231,
        51549397878,
        54583169839,
        57858895605,
        44461445112,
        43396022788,
        57363002161,
        57681239523,
        57948756063,
        56347602044,
        56650271627,
        39284822769,
        44851970418
      ],
      "customStats": {},
      "counters": {},
      "concurrency": 1674,
      "pendingRequests": 15632,
      "scenariosAvoided": 0
    },
    {
      "timestamp": "2020-07-14T16:32:13.691Z",
      "scenariosCreated": 0,
      "scenariosCompleted": 404,
      "requestsCompleted": 404,
      "latency": {
        "min": 22775,
        "max": 59998.5,
        "median": 48290.9,
        "p95": 58234.8,
        "p99": 59566.8
      },
      "rps": {
        "count": 0,
        "mean": null
      },
      "scenarioDuration": {
        "min": 22776.4,
        "max": 60000.2,
        "median": 48292.3,
        "p95": 58236.3,
        "p99": 59568.3
      },
      "scenarioCounts": {},
      "errors": {
        "ESOCKETTIMEDOUT": 389
      },
      "codes": {
        "200": 35,
        "502": 369
      },
      "matches": 0,
      "latencies": [
        39718122342,
        56618267391,
        57619140665,
        56586440792,
        45354126429,
        46454670475,
        47422010361,
        28190042746,
        30190397956,
        52243824064,
        44445090577,
        25711325498,
        27947188137,
        55013371895,
        51080545229,
        49314002076,
        40147869595,
        28014997525,
        46881220954,
        39081607551,
        59180888155,
        36315208532,
        52481481621,
        29549124535,
        33482437124,
        45682079961,
        49148756133,
        48148986274,
        36339979890,
        24641854944,
        46175005646,
        48674958068,
        24610425961,
        56476450068,
        54610391537,
        57644194002,
        57678051554,
        58178781036,
        51778928746,
        43813830365,
        58563202854,
        46764536626,
        48565103641,
        53865526833,
        41333297483,
        41833942503,
        29001800998,
        36702034168,
        51968127551,
        56269288858,
        56669800110,
        56703670726,
        51534997847,
        50002847394,
        47837072195,
        33302894351,
        24339281203,
        54505349578,
        41573069191,
        46806687623,
        22774989691,
        27075419534,
        51408325639,
        48442337184,
        32181774014,
        23782753614,
        53582247962,
        29083886632,
        50790072970,
        23724558639,
        34757588841,
        59623408608,
        59690245283,
        39357782801,
        44697323891,
        59998472095,
        38500330190,
        56233517174,
        56801005261,
        43301775775,
        37969696762,
        53436300654,
        52870211146,
        56137251190,
        49138266525,
        58071751264,
        43505660022,
        59992532643,
        48193892754,
        49694575664,
        50295151973,
        27329982287,
        27797287556,
        35030850588,
        46664241004,
        25065680508,
        40399110431,
        31837425631,
        46571393846,
        51471861830,
        42106220748,
        37340346617,
        30474552593,
        52207505154,
        58107870525,
        28609576754,
        25961296037,
        25928870208,
        25862900017,
        22796497649,
        25997583083,
        25772257674,
        25824683672,
        25859232416,
        56247765503,
        58148685015,
        39716824877,
        39117510069,
        37518218477,
        57517956476,
        40852730726,
        56052643133,
        56986510720,
        50787334523,
        55321058898,
        51362605330,
        55030149587,
        26965172070,
        52129307320,
        28966498012,
        30400377847,
        29934268609,
        35701250872,
        39801738632,
        23069640763,
        32536380649,
        58902662306,
        47936994797,
        49470848872,
        53171403069,
        30506125856,
        53572459563,
        41773533111,
        51940290206,
        40107576681,
        56607735214,
        58241779065,
        47842912356,
        29344268792,
        24511774701,
        59058758640,
        56726717057,
        33494983578,
        59394603122,
        56228707269,
        46563503028,
        56330494821,
        56431074470,
        51997852017,
        42399579374,
        53166284217,
        56276012652,
        41611100759,
        29645611055,
        55245337279,
        47812919761,
        45546962664,
        40681084338,
        24215677064,
        30815858501,
        36049654808,
        32750385898,
        52783449510,
        27818440593,
        33318703604,
        52085235473,
        50652476157,
        44953866161,
        30621709270,
        52854761314,
        42555668000,
        52596188259,
        33798011876,
        48531438113,
        36165568706,
        24066998011,
        43367012654,
        47567392392,
        55101040725,
        42768766009,
        38736130324,
        32503619567,
        57536975200,
        56137644291,
        28305982608,
        25073270624,
        53743314734,
        41844489897,
        56777847870,
        57444591918,
        50296087187,
        53930278477,
        35032351680,
        51998938362,
        50932895922,
        53299491937,
        52067375402,
        39068560177,
        49435377488,
        59068994887,
        55604425452,
        57576761889,
        44344775127,
        43012154133,
        54479380533,
        47013854828,
        45847879563,
        42637344416,
        54937649482,
        38339185069,
        53272594006,
        55239824285,
        36740973515,
        51907191969,
        56973665047,
        58507196189,
        54559331796,
        56693584295,
        52261041991,
        58894767489,
        48695797544,
        53762856072,
        53263833337,
        43518505252,
        49419098844,
        58286140595,
        55953677378,
        49554578746,
        52788256547,
        50754990741,
        55828476078,
        41330087528,
        54930218570,
        51297617891,
        47098430168,
        52098818660,
        39133220425,
        49266711791,
        43200817151,
        51901027927,
        36202279888,
        36035436717,
        56135910832,
        54236789373,
        27638218174,
        41405059842,
        53177080005,
        57844877820,
        55379051813,
        35947086116,
        46879939551,
        56780920086,
        57248140861,
        52381788061,
        45350414340,
        56383943107,
        25998263101,
        59518663853,
        59186245431,
        56087080517,
        55287816956,
        54321843533,
        50022586595,
        51023318899,
        51257210247,
        47772753499,
        50640786083,
        56058127474,
        28760101513,
        26693540140,
        31126880492,
        42293184623,
        49859724932,
        53026561506,
        53860048881,
        49043670270,
        51277053520,
        37961184251,
        56927137728,
        37394748194,
        35694947851,
        51560496115,
        58160957925,
        44946213324,
        31413767999,
        30116357946,
        51437690556,
        28939412979,
        39106405519,
        53039815570,
        52740561199,
        40641689961,
        56741586493,
        39876107816,
        52276137859,
        48176868542,
        51977336435,
        28445526499,
        43712076085,
        25879962767,
        33046803263,
        48656101309,
        37657421400,
        55057376542,
        27225853335,
        50125240838,
        45326319487,
        24926512256,
        49727197595,
        55494185654,
        28295764569,
        30096204463,
        28430166572,
        37830800961,
        38931229138,
        38965270172,
        58798401589,
        54565795301,
        54475176119,
        59009932093,
        49811003734,
        50811710473,
        52545322113,
        54745823451,
        48580167267,
        54180457307,
        48448140552,
        45049460719,
        32117589528,
        50217827584,
        39719029097,
        44019678570,
        48387902264,
        46639470616,
        26541193273,
        55807259870,
        55374704084,
        53243107034,
        55509899360,
        44977069043,
        54731004132,
        50732013210,
        58231836024,
        47700077875,
        48733998633,
        53034505386,
        43110482159,
        39078312000,
        40579276219,
        29913497348,
        49913585475,
        59080485770,
        45314900345,
        34215957641,
        39050189730,
        51072362536,
        39407187101,
        53207317206,
        30042230575,
        57341789390,
        39709822766,
        36610581506,
        44348597267,
        47982604371,
        45783385542,
        38018056550,
        35316837054,
        30417995576,
        55884287569,
        49851804005,
        58718759405,
        33786964408,
        33387507426,
        36587900658,
        30888640501,
        44321963572,
        52888962146,
        57850874492,
        55385166921,
        48819432730,
        54986441241,
        44054184774,
        47954666802,
        30655924347,
        50639425569,
        44207223348,
        53740917444,
        46241865726,
        50542227735,
        55576036799,
        53810009109,
        52910537317,
        51587168124,
        44188419431
      ],
      "customStats": {},
      "counters": {},
      "concurrency": 881,
      "pendingRequests": 15228,
      "scenariosAvoided": 0
    },
    {
      "timestamp": "2020-07-14T16:32:23.686Z",
      "scenariosCreated": 0,
      "scenariosCompleted": 132,
      "requestsCompleted": 132,
      "latency": {
        "min": 32908.5,
        "max": 59881.2,
        "median": 51348.6,
        "p95": 58932.5,
        "p99": 59838.2
      },
      "rps": {
        "count": 0,
        "mean": null
      },
      "scenarioDuration": {
        "min": 32909.9,
        "max": 59883.2,
        "median": 51350.1,
        "p95": 58934,
        "p99": 59839.8
      },
      "scenarioCounts": {},
      "errors": {
        "ESOCKETTIMEDOUT": 294
      },
      "codes": {
        "200": 57,
        "502": 75
      },
      "matches": 0,
      "latencies": [
        52592750244,
        52127173014,
        34128536098,
        59828778529,
        43330215372,
        53392854723,
        46960760526,
        33328676637,
        49295329785,
        54962465052,
        46863344547,
        56063630282,
        34198400450,
        50998792095,
        58300139168,
        49568191490,
        42235882870,
        58935852773,
        58902636295,
        57602426072,
        59669992766,
        57337340769,
        43633952912,
        50635023533,
        45469283088,
        42670167976,
        44037164023,
        40704649788,
        43071774733,
        55105225349,
        58038916118,
        49073249474,
        39940787786,
        32908505972,
        59650214132,
        56784957086,
        53885401260,
        55002253343,
        46286684197,
        45287625210,
        43321235332,
        41988182929,
        48588092545,
        50452796239,
        42721857734,
        36825634662,
        35491874080,
        32959626529,
        40494163809,
        37928210284,
        56875531590,
        36967586591,
        38068491937,
        53935196710,
        55014662356,
        55316137226,
        55417764868,
        51452098144,
        54886225955,
        50987251269,
        51121372817,
        50222173342,
        50023146178,
        49590654328,
        49957915865,
        55191136873,
        54859133822,
        43693971310,
        49228002617,
        49235936325,
        56102798532,
        57704155771,
        57004613844,
        54741799914,
        54176299170,
        39276996774,
        51245043652,
        44879424944,
        35801888855,
        51002630940,
        53803380612,
        45204099600,
        54005016641,
        51139391508,
        56597709752,
        56232337291,
        56166584192,
        56134032275,
        52935005495,
        56035601178,
        53003292838,
        52604063384,
        52273736918,
        51808910065,
        56409541498,
        56077064830,
        55044548858,
        39712658886,
        56579459915,
        50980392045,
        52885475231,
        41954073116,
        40555105879,
        49622270137,
        55756182772,
        41591000299,
        54305930063,
        54174564466,
        59808560460,
        56309622959,
        44444196214,
        56680822054,
        52559705683,
        46461158307,
        42032802629,
        40403166290,
        58336986066,
        58037981518,
        50149165863,
        54816768382,
        44151603304,
        47118943596,
        40086022755,
        56986224163,
        43222149146,
        39505877316,
        59881166929,
        59192509863,
        55693633626,
        54402926965,
        56885340328,
        57553265773
      ],
      "customStats": {},
      "counters": {},
      "concurrency": 455,
      "pendingRequests": 15096,
      "scenariosAvoided": 0
    },
    {
      "timestamp": "2020-07-14T16:32:33.681Z",
      "scenariosCreated": 0,
      "scenariosCompleted": 57,
      "requestsCompleted": 57,
      "latency": {
        "min": 41036.1,
        "max": 59861.4,
        "median": 55233,
        "p95": 59739.7,
        "p99": 59853.8
      },
      "rps": {
        "count": 0,
        "mean": null
      },
      "scenarioDuration": {
        "min": 41037.5,
        "max": 59862.9,
        "median": 55234.5,
        "p95": 59741.6,
        "p99": 59855.3
      },
      "scenarioCounts": {},
      "errors": {
        "ESOCKETTIMEDOUT": 197
      },
      "codes": {
        "200": 15,
        "502": 42
      },
      "matches": 0,
      "latencies": [
        54359128526,
        53393835322,
        49628029967,
        47694971586,
        47463271540,
        45203270597,
        55071449820,
        46905893982,
        45505998822,
        45367800413,
        58868980931,
        59469362840,
        46903519717,
        55970073601,
        57237060003,
        58296456004,
        52964558225,
        50965236971,
        55233040138,
        42734241884,
        51667988821,
        41036063506,
        56536180760,
        59737067420,
        57837912209,
        48139173588,
        44773414660,
        59741189607,
        58742779678,
        59076829355,
        59410982704,
        57445414671,
        56446164210,
        46180773858,
        45075486030,
        58806672727,
        56311159428,
        58912948597,
        58280848969,
        59193553794,
        59861372181,
        44074015864,
        49889022267,
        54045712908,
        57926415805,
        47289283980,
        57564665596,
        51277936506,
        52251057752,
        56818588321,
        59753117922,
        57808748343,
        58542828844,
        58410628149,
        59444767943,
        55179089055,
        53213279032
      ],
      "customStats": {},
      "counters": {},
      "concurrency": 201,
      "pendingRequests": 15039,
      "scenariosAvoided": 0
    },
    {
      "timestamp": "2020-07-14T16:32:43.682Z",
      "scenariosCreated": 0,
      "scenariosCompleted": 23,
      "requestsCompleted": 23,
      "latency": {
        "min": 52058.4,
        "max": 59606.4,
        "median": 57176.5,
        "p95": 59466.1,
        "p99": 59606.4
      },
      "rps": {
        "count": 0,
        "mean": null
      },
      "scenarioDuration": {
        "min": 52060.2,
        "max": 59608,
        "median": 57178.1,
        "p95": 59467.8,
        "p99": 59608
      },
      "scenarioCounts": {},
      "errors": {
        "ESOCKETTIMEDOUT": 176
      },
      "codes": {
        "200": 12,
        "502": 11
      },
      "matches": 0,
      "latencies": [
        57310443348,
        57511523468,
        53132798065,
        54334399095,
        59390591737,
        52058358397,
        59606404969,
        53424677415,
        58460956353,
        58299594684,
        57534081615,
        55801787541,
        55069191844,
        54370157426,
        55837657479,
        55171857274,
        56642194801,
        57176520501,
        56377400452,
        57273005597,
        59301844953,
        59074376414,
        58113980860
      ],
      "customStats": {},
      "counters": {},
      "concurrency": 2,
      "pendingRequests": 15016,
      "scenariosAvoided": 0
    },
    {
      "timestamp": "2020-07-14T16:32:43.752Z",
      "scenariosCreated": 0,
      "scenariosCompleted": 0,
      "requestsCompleted": 0,
      "latency": {
        "min": null,
        "max": null,
        "median": null,
        "p95": null,
        "p99": null
      },
      "rps": {
        "count": 0,
        "mean": null
      },
      "scenarioDuration": {
        "min": null,
        "max": null,
        "median": null,
        "p95": null,
        "p99": null
      },
      "scenarioCounts": {},
      "errors": {
        "ESOCKETTIMEDOUT": 2
      },
      "codes": {},
      "matches": 0,
      "latencies": [],
      "customStats": {},
      "counters": {},
      "concurrency": 0,
      "pendingRequests": 15016,
      "scenariosAvoided": 0
    }
  ]
}